image2numpy/__init__.py
image2numpy/extract_valid_cube.py
image2numpy/load_png_to_3d_array.py
image2numpy/save_3d_array_as_gray_images.py
image2numpy-0.0.0.dist-info/licenses/LICENSE
image2numpy-0.0.0.dist-info/METADATA
image2numpy-0.0.0.dist-info/WHEEL
image2numpy-0.0.0.dist-info/top_level.txt
image2numpy-0.0.0.dist-info/RECORD
