Metadata-Version: 2.4
Name: image2numpy
Version: 0.0.0
Summary: A program for bidirectional conversion between grayscale image sequences and numpy ndarrays.
Author-email: GGN_2015 <neko@jlulug.org>
License: MIT License
Requires-Python: >=3.10
License-File: LICENSE
Requires-Dist: pillow
Requires-Dist: opencv-python
Requires-Dist: numpy
Dynamic: license-file
